marshallEngine/__init__.py
marshallEngine/__version__.py
marshallEngine/cl_utils.py
marshallEngine/default_settings.yaml
marshallEngine/test_settings.yaml
marshallEngine/utKit.py
marshallEngine/commonutils/__init__.py
marshallEngine/commonutils/getpackagepath.py
marshallEngine/feeders/__init__.py
marshallEngine/feeders/data.py
marshallEngine/feeders/images.py
marshallEngine/feeders/atels/__init__.py
marshallEngine/feeders/atels/data.py
marshallEngine/feeders/atels/images.py
marshallEngine/feeders/atels/tests/__init__.py
marshallEngine/feeders/atels/tests/test_data.py
marshallEngine/feeders/atlas/__init__.py
marshallEngine/feeders/atlas/data.py
marshallEngine/feeders/atlas/images.py
marshallEngine/feeders/atlas/lightcurve.py
marshallEngine/feeders/atlas/tests/__init__.py
marshallEngine/feeders/atlas/tests/test_data.py
marshallEngine/feeders/atlas/tests/test_images.py
marshallEngine/feeders/atlas/tests/test_lightcurve.py
marshallEngine/feeders/panstarrs/__init__.py
marshallEngine/feeders/panstarrs/data.py
marshallEngine/feeders/panstarrs/images.py
marshallEngine/feeders/panstarrs/tests/__init__.py
marshallEngine/feeders/panstarrs/tests/test_data.py
marshallEngine/feeders/panstarrs/tests/test_images.py
marshallEngine/feeders/tests/__init__.py
marshallEngine/feeders/tests/test_data.py
marshallEngine/feeders/tests/test_images.py
marshallEngine/feeders/tns/__init__.py
marshallEngine/feeders/tns/data.py
marshallEngine/feeders/tns/images.py
marshallEngine/feeders/tns/tests/__init__.py
marshallEngine/feeders/tns/tests/test_data.py
marshallEngine/feeders/tns/tests/test_images.py
marshallEngine/feeders/useradded/__init__.py
marshallEngine/feeders/useradded/data.py
marshallEngine/feeders/useradded/images.py
marshallEngine/feeders/useradded/tests/__init__.py
marshallEngine/feeders/useradded/tests/test_data.py
marshallEngine/feeders/useradded/tests/test_images.py
marshallEngine/feeders/ztf/__init__.py
marshallEngine/feeders/ztf/data.py
marshallEngine/feeders/ztf/images.py
marshallEngine-1.0.10.dist-info/LICENSE
marshallEngine-1.0.10.dist-info/METADATA
marshallEngine-1.0.10.dist-info/WHEEL
marshallEngine-1.0.10.dist-info/entry_points.txt
marshallEngine-1.0.10.dist-info/top_level.txt
marshallEngine-1.0.10.dist-info/RECORD
