Metadata-Version: 2.1
Name: marshallEngine
Version: 1.0.10
Summary: the engine behind the marshall webapp
Home-page: https://github.com/thespacedoctor/marshallEngine
Download-URL: https://github.com/thespacedoctor/marshallEngine/archive/v1.0.10.zip
Author: David Young
Author-email: davidrobertyoung@gmail.com
License: MIT
Keywords: astronomy, marshall, webapp
Platform: UNKNOWN
Classifier: Development Status :: 4 - Beta
Classifier: License :: OSI Approved :: MIT License
Classifier: Programming Language :: Python :: 3.7
Classifier: Topic :: Utilities
License-File: LICENSE
Requires-Dist: pyyaml
Requires-Dist: marshallEngine
Requires-Dist: fundamentals
Requires-Dist: astrocalc
Requires-Dist: hmpty
Requires-Dist: astropy
Requires-Dist: matplotlib
Requires-Dist: panstamps
Requires-Dist: transientNamer
Requires-Dist: tornado
Requires-Dist: numpy
Requires-Dist: gitpython
Requires-Dist: atelParser
